LICENSE
setup.py
clickzetta_low_touch_tool.egg-info/PKG-INFO
clickzetta_low_touch_tool.egg-info/SOURCES.txt
clickzetta_low_touch_tool.egg-info/dependency_links.txt
clickzetta_low_touch_tool.egg-info/not-zip-safe
clickzetta_low_touch_tool.egg-info/requires.txt
clickzetta_low_touch_tool.egg-info/top_level.txt
low_touch_tool/__init__.py
low_touch_tool/main.py
low_touch_tool/version.py
low_touch_tool/pages/__init__.py
low_touch_tool/pages/connnection_testing.py
low_touch_tool/pages/data_verification.py
low_touch_tool/pages/sql_translation.py
low_touch_tool/pages/unify.py
low_touch_tool/util/__init__.py
low_touch_tool/util/connect_util.py
low_touch_tool/util/validation_util.py