Metadata-Version: 2.1
Name: clickzetta-low-touch-tool
Version: 0.0.1
Summary: clickzetta low touch tool
Home-page: https://www.yunqi.tech/
Author: mocun
Author-email: hanmiao.li@clickzetta.com
Platform: Posix; MacOS X;
Requires-Python: >=3.7
Provides-Extra: all
License-File: LICENSE
